LICENSE.md
MANIFEST.in
README.rst
pyproject.toml
requirements.core.txt
requirements.txt
setup.py
core_oaipmh_harvester_app/__init__.py
core_oaipmh_harvester_app/admin.py
core_oaipmh_harvester_app/apps.py
core_oaipmh_harvester_app/discover.py
core_oaipmh_harvester_app/menus.py
core_oaipmh_harvester_app/settings.py
core_oaipmh_harvester_app/tasks.py
core_oaipmh_harvester_app/urls.py
core_oaipmh_harvester_app.egg-info/PKG-INFO
core_oaipmh_harvester_app.egg-info/SOURCES.txt
core_oaipmh_harvester_app.egg-info/dependency_links.txt
core_oaipmh_harvester_app.egg-info/requires.txt
core_oaipmh_harvester_app.egg-info/top_level.txt
core_oaipmh_harvester_app/commons/__init__.py
core_oaipmh_harvester_app/commons/rights.py
core_oaipmh_harvester_app/components/__init__.py
core_oaipmh_harvester_app/components/mongo/__init__.py
core_oaipmh_harvester_app/components/mongo/api.py
core_oaipmh_harvester_app/components/mongo/models.py
core_oaipmh_harvester_app/components/oai_harvester_metadata_format/__init__.py
core_oaipmh_harvester_app/components/oai_harvester_metadata_format/api.py
core_oaipmh_harvester_app/components/oai_harvester_metadata_format/models.py
core_oaipmh_harvester_app/components/oai_harvester_metadata_format_set/__init__.py
core_oaipmh_harvester_app/components/oai_harvester_metadata_format_set/api.py
core_oaipmh_harvester_app/components/oai_harvester_metadata_format_set/models.py
core_oaipmh_harvester_app/components/oai_harvester_set/__init__.py
core_oaipmh_harvester_app/components/oai_harvester_set/api.py
core_oaipmh_harvester_app/components/oai_harvester_set/models.py
core_oaipmh_harvester_app/components/oai_identify/__init__.py
core_oaipmh_harvester_app/components/oai_identify/api.py
core_oaipmh_harvester_app/components/oai_identify/models.py
core_oaipmh_harvester_app/components/oai_record/__init__.py
core_oaipmh_harvester_app/components/oai_record/api.py
core_oaipmh_harvester_app/components/oai_record/models.py
core_oaipmh_harvester_app/components/oai_registry/__init__.py
core_oaipmh_harvester_app/components/oai_registry/api.py
core_oaipmh_harvester_app/components/oai_registry/models.py
core_oaipmh_harvester_app/components/oai_verbs/__init__.py
core_oaipmh_harvester_app/components/oai_verbs/api.py
